h_assets/__init__.py
h_assets/_cached_file.py
h_assets/environment.py
h_assets/view.py
h_assets-1.1.0.dist-info/licenses/LICENSE
h_assets-1.1.0.dist-info/METADATA
h_assets-1.1.0.dist-info/WHEEL
h_assets-1.1.0.dist-info/top_level.txt
h_assets-1.1.0.dist-info/RECORD
