Metadata-Version: 2.4
Name: h-assets
Version: 1.1.0
Summary: Pyramid views for serving collections of compiled static assets (eg. bundles of JavaScript and CSS).
Project-URL: Repository, https://github.com/hypothesis/h-assets
Project-URL: Issues, https://github.com/hypothesis/h-assets/issues
Project-URL: Changelog, https://github.com/hypothesis/h-assets/releases
Classifier: Programming Language :: Python :: 3
Classifier: License :: OSI Approved :: BSD License
Classifier: Intended Audience :: Developers
Requires-Python: >=3.9
License-File: LICENSE
Requires-Dist: pyramid
Dynamic: license-file
